mfig/__init__.py
mfig/mfig.py
mfig-0.2.5.dist-info/LICENSE
mfig-0.2.5.dist-info/METADATA
mfig-0.2.5.dist-info/WHEEL
mfig-0.2.5.dist-info/entry_points.txt
mfig-0.2.5.dist-info/top_level.txt
mfig-0.2.5.dist-info/zip-safe
mfig-0.2.5.dist-info/RECORD
