Metadata-Version: 2.1
Name: mfig
Version: 0.2.5
Summary: A tool for merging multiple figures into one
Author: Koushik Naskar
Author-email: koushik.naskar9@gmail.com
License: MIT
Project-URL: Source Code, https://github.com/Koushikphy/mfig
Keywords: Image merging
Classifier: Development Status :: 5 - Production/Stable
Classifier: Environment :: Console
Classifier: Intended Audience :: Science/Research
Classifier: Natural Language :: English
Classifier: License :: OSI Approved :: MIT License
Classifier: Operating System :: OS Independent
Classifier: Programming Language :: Python :: Implementation :: CPython
Classifier: Topic :: System :: Shells
Classifier: Programming Language :: Python :: 3.6
Requires-Python: >=3.6
License-File: LICENSE
